{
    "Feuille ancienne pétrifiée" : {
        "raid": "MC",
        "bosses": ["Chambellan Executus"]
    },
    "Anneau de cautérisation" : {
        "raid": "MC",
        "bosses": ["Chambellan Executus"]
    },
    "Grèves du Coeur du Magma" : {
        "raid": "MC",
        "bosses": ["Chambellan Executus"]
    },
    "Dent de chien du magma" : {
        "raid": "MC",
        "bosses": ["Chambellan Executus"]
    },
    "Drague-lave de Finkle" : {
        "raid": "MC",
        "bosses": ["Chambellan Executus"]
    },
    "Epaulières de garde du feu" : {
        "raid": "MC",
        "bosses": ["Chambellan Executus"]
    },
    "Cape ignifugée" : {
        "raid": "MC",
        "bosses": ["Chambellan Executus"]
    },
    "Gants de la flamme hypnotique" : {
        "raid": "MC",
        "bosses": ["Chambellan Executus"]
    },
    "Echarpe des secrets murmurés" : {
        "raid": "MC",
        "bosses": ["Chambellan Executus"]
    },
    "L'Oeil de la divinité" : {
        "raid": "MC",
        "bosses": ["Chambellan Executus"]
    },
    "Spallières de croissance sauvage" : {
        "raid": "MC",
        "bosses": ["Chambellan Executus"]
    },
    "Garde-poignets de vrai vol" : {
        "raid": "MC",
        "bosses": ["Chambellan Executus"]
    }
}